{
  "project_info": {
    "project_number": "714420501810",
    "project_id": "joyeria-95fe7",
    "storage_bucket": "joyeria-95fe7.firebasestorage.app"
  },
  "client": [
    {
      "client_info": {
        "mobilesdk_app_id": "1:714420501810:android:874dd854955fbde697eb2b",
        "android_client_info": {
          "package_name": "com.selvi.joyeria"
        }
      },
      "oauth_client": [],
      "api_key": [
        {
          "current_key": "AIzaSyC4RpMkCn2sVfrjAvCcPm5IClnPR91QjXM"
        }
      ],
      "services": {
        "appinvite_service": {
          "other_platform_oauth_client": []
        }
      }
    }
  ],
  "configuration_version": "1"
}